{
  "data": {
    "article": {},
    "attachments": {},
    "author_id": "1752538285459795968",
    "conversation_id": "1913101722828017999",
    "created_at": "2025-04-18T21:21:21.000Z",
    "edit_controls": {
      "editable_until": "2025-04-18T22:21:21.000Z",
      "edits_remaining": 5,
      "is_edit_eligible": false
    },
    "edit_history_tweet_ids": [
      "1913342107684901149"
    ],
    "entities": {
      "annotations": [
        {
          "end": 34,
          "normalized_text": "黄仁勋",
          "probability": 0.2507,
          "start": 32,
          "type": "Person"
        }
      ],
      "mentions": [
        {
          "end": 11,
          "id": "1302241099843477504",
          "start": 0,
          "username": "Cicada0001"
        },
        {
          "end": 23,
          "id": "1422919666305888264",
          "start": 12,
          "username": "0x88FFA357"
        },
        {
          "end": 31,
          "id": "50683",
          "start": 24,
          "username": "dingyi"
        }
      ]
    },
    "geo": {},
    "id": "1913342107684901149",
    "in_reply_to_user_id": "1302241099843477504",
    "lang": "ja",
    "note_tweet": {
      "entities": {}
    },
    "possibly_sensitive": false,
    "public_metrics": {
      "bookmark_count": 0,
      "impression_count": 0,
      "like_count": 0,
      "quote_count": 0,
      "reply_count": 0,
      "retweet_count": 0
    },
    "referenced_tweets": [
      {
        "id": "1913257983502680306",
        "type": "replied_to"
      }
    ],
    "reply_settings": "everyone",
    "text": "@Cicada0001 @0x88FFA357 @dingyi 黄仁勋（中国限定版）"
  },
  "includes": {
    "tweets": [
      {
        "article": {},
        "attachments": {},
        "author_id": "1752538285459795968",
        "conversation_id": "1913101722828017999",
        "created_at": "2025-04-18T21:21:21.000Z",
        "edit_controls": {
          "editable_until": "2025-04-18T22:21:21.000Z",
          "edits_remaining": 5,
          "is_edit_eligible": false
        },
        "edit_history_tweet_ids": [
          "1913342107684901149"
        ],
        "entities": {
          "annotations": [
            {
              "end": 34,
              "normalized_text": "黄仁勋",
              "probability": 0.2507,
              "start": 32,
              "type": "Person"
            }
          ],
          "mentions": [
            {
              "end": 11,
              "id": "1302241099843477504",
              "start": 0,
              "username": "Cicada0001"
            },
            {
              "end": 23,
              "id": "1422919666305888264",
              "start": 12,
              "username": "0x88FFA357"
            },
            {
              "end": 31,
              "id": "50683",
              "start": 24,
              "username": "dingyi"
            }
          ]
        },
        "geo": {},
        "id": "1913342107684901149",
        "in_reply_to_user_id": "1302241099843477504",
        "lang": "ja",
        "note_tweet": {
          "entities": {}
        },
        "possibly_sensitive": false,
        "public_metrics": {
          "bookmark_count": 0,
          "impression_count": 0,
          "like_count": 0,
          "quote_count": 0,
          "reply_count": 0,
          "retweet_count": 0
        },
        "referenced_tweets": [
          {
            "id": "1913257983502680306",
            "type": "replied_to"
          }
        ],
        "reply_settings": "everyone",
        "text": "@Cicada0001 @0x88FFA357 @dingyi 黄仁勋（中国限定版）"
      },
      {
        "article": {},
        "attachments": {},
        "author_id": "1302241099843477504",
        "conversation_id": "1913101722828017999",
        "created_at": "2025-04-18T15:47:04.000Z",
        "edit_controls": {
          "editable_until": "2025-04-18T16:47:04.000Z",
          "edits_remaining": 5,
          "is_edit_eligible": false
        },
        "edit_history_tweet_ids": [
          "1913257983502680306"
        ],
        "entities": {
          "mentions": [
            {
              "end": 11,
              "id": "1422919666305888264",
              "start": 0,
              "username": "0x88FFA357"
            },
            {
              "end": 19,
              "id": "50683",
              "start": 12,
              "username": "dingyi"
            }
          ]
        },
        "geo": {},
        "id": "1913257983502680306",
        "in_reply_to_user_id": "1422919666305888264",
        "lang": "ja",
        "note_tweet": {
          "entities": {}
        },
        "possibly_sensitive": false,
        "public_metrics": {
          "bookmark_count": 0,
          "impression_count": 217,
          "like_count": 15,
          "quote_count": 0,
          "reply_count": 0,
          "retweet_count": 0
        },
        "referenced_tweets": [
          {
            "id": "1913211635726160161",
            "type": "replied_to"
          }
        ],
        "reply_settings": "everyone",
        "text": "@0x88FFA357 @dingyi 黄仁勋 D"
      }
    ],
    "users": [
      {
        "created_at": "2024-01-31T03:44:57.000Z",
        "description": "你若爱我，我亦如此",
        "id": "1752538285459795968",
        "location": "人间",
        "name": "月影独下",
        "pinned_tweet_id": "1898188832119701714",
        "profile_image_url": "https://pbs.twimg.com/profile_images/1839458351497052160/HTYx9mD2_normal.jpg",
        "protected": false,
        "public_metrics": {
          "followers_count": 82,
          "following_count": 73,
          "like_count": 6131,
          "listed_count": 1,
          "media_count": 87,
          "tweet_count": 1442
        },
        "username": "tadatsukiei",
        "verified": false
      },
      {
        "created_at": "2020-09-05T13:44:22.000Z",
        "description": "在平坦的路面上曲折前行",
        "entities": {
          "url": {
            "urls": [
              {
                "display_url": "cicada000.work",
                "end": 23,
                "expanded_url": "https://cicada000.work",
                "start": 0,
                "url": "https://t.co/wS5cjpCj75"
              }
            ]
          }
        },
        "id": "1302241099843477504",
        "location": "银河系第三旋臂",
        "name": "ℂ𝕚𝕔𝕒𝕕𝕒𝟘𝟘𝟘",
        "pinned_tweet_id": "1874311512275439959",
        "profile_image_url": "https://pbs.twimg.com/profile_images/1769749312010153984/M795r57s_normal.jpg",
        "protected": false,
        "public_metrics": {
          "followers_count": 448,
          "following_count": 685,
          "like_count": 120862,
          "listed_count": 9,
          "media_count": 1293,
          "tweet_count": 13496
        },
        "url": "https://t.co/wS5cjpCj75",
        "username": "Cicada0001",
        "verified": false
      },
      {
        "created_at": "2021-08-04T13:57:51.000Z",
        "description": "",
        "entities": {
          "url": {
            "urls": [
              {
                "display_url": "nvme0n1p.dev",
                "end": 23,
                "expanded_url": "http://nvme0n1p.dev",
                "start": 0,
                "url": "https://t.co/M3EWZGYw8X"
              }
            ]
          }
        },
        "id": "1422919666305888264",
        "location": "额",
        "name": "溴化锂",
        "pinned_tweet_id": "1818346355989135620",
        "profile_image_url": "https://pbs.twimg.com/profile_images/1816087287903707136/3vMr5LZj_normal.jpg",
        "protected": false,
        "public_metrics": {
          "followers_count": 1548,
          "following_count": 2220,
          "like_count": 131967,
          "listed_count": 9,
          "media_count": 562,
          "tweet_count": 8939
        },
        "url": "https://t.co/M3EWZGYw8X",
        "username": "0x88FFA357",
        "verified": false
      },
      {
        "created_at": "2006-12-08T15:10:12.000Z",
        "description": "Design Newsletter ‣ https://t.co/f9dMX5LXfz\nDesign Engineer News ‣ https://t.co/qmrK2xQOz8",
        "entities": {
          "description": {
            "urls": [
              {
                "display_url": "quaily.com/dingyi",
                "end": 43,
                "expanded_url": "https://quaily.com/dingyi",
                "start": 20,
                "url": "https://t.co/f9dMX5LXfz"
              },
              {
                "display_url": "news.dex.group",
                "end": 90,
                "expanded_url": "https://news.dex.group/",
                "start": 67,
                "url": "https://t.co/qmrK2xQOz8"
              }
            ]
          },
          "url": {
            "urls": [
              {
                "display_url": "ding.one",
                "end": 23,
                "expanded_url": "http://ding.one",
                "start": 0,
                "url": "https://t.co/cf71jdxlkm"
              }
            ]
          }
        },
        "id": "50683",
        "location": " ‣",
        "name": "ding.one",
        "pinned_tweet_id": "1913173455002042545",
        "profile_image_url": "https://pbs.twimg.com/profile_images/1508523236560027650/DA1UcGmv_normal.jpg",
        "protected": false,
        "public_metrics": {
          "followers_count": 162438,
          "following_count": 4304,
          "like_count": 4546,
          "listed_count": 472,
          "media_count": 1872,
          "tweet_count": 52001
        },
        "url": "https://t.co/cf71jdxlkm",
        "username": "dingyi",
        "verified": true
      }
    ]
  }
}