{
  "data": {
    "article": {},
    "attachments": {
      "media_keys": [
        "3_2065064059582734336"
      ]
    },
    "author_id": "1752538285459795968",
    "conversation_id": "2065064064016060576",
    "created_at": "2026-06-11T13:30:14.000Z",
    "edit_controls": {
      "editable_until": "2026-06-11T14:30:14.000Z",
      "edits_remaining": 5,
      "is_edit_eligible": true
    },
    "edit_history_tweet_ids": [
      "2065064064016060576"
    ],
    "entities": {
      "urls": [
        {
          "display_url": "pic.x.com/zqRm9zd4RA",
          "end": 37,
          "expanded_url": "https://x.com/tadatsukiei/status/2065064064016060576/photo/1",
          "media_key": "3_2065064059582734336",
          "start": 14,
          "url": "https://t.co/zqRm9zd4RA"
        }
      ]
    },
    "geo": {},
    "id": "2065064064016060576",
    "lang": "zh",
    "note_tweet": {
      "entities": {}
    },
    "possibly_sensitive": false,
    "public_metrics": {
      "bookmark_count": 0,
      "impression_count": 0,
      "like_count": 0,
      "quote_count": 0,
      "reply_count": 0,
      "retweet_count": 0
    },
    "reply_settings": "everyone",
    "text": "648fo纪念～感谢大家🥰 https://t.co/zqRm9zd4RA"
  },
  "includes": {
    "media": [
      {
        "height": 477,
        "media_key": "3_2065064059582734336",
        "public_metrics": {},
        "type": "photo",
        "url": "https://pbs.twimg.com/media/HKiU0i3a4AA727u.jpg",
        "width": 921
      }
    ],
    "tweets": [
      {
        "article": {},
        "attachments": {
          "media_keys": [
            "3_2065064059582734336"
          ]
        },
        "author_id": "1752538285459795968",
        "conversation_id": "2065064064016060576",
        "created_at": "2026-06-11T13:30:14.000Z",
        "edit_controls": {
          "editable_until": "2026-06-11T14:30:14.000Z",
          "edits_remaining": 5,
          "is_edit_eligible": true
        },
        "edit_history_tweet_ids": [
          "2065064064016060576"
        ],
        "entities": {
          "urls": [
            {
              "display_url": "pic.x.com/zqRm9zd4RA",
              "end": 37,
              "expanded_url": "https://x.com/tadatsukiei/status/2065064064016060576/photo/1",
              "media_key": "3_2065064059582734336",
              "start": 14,
              "url": "https://t.co/zqRm9zd4RA"
            }
          ]
        },
        "geo": {},
        "id": "2065064064016060576",
        "lang": "zh",
        "note_tweet": {
          "entities": {}
        },
        "possibly_sensitive": false,
        "public_metrics": {
          "bookmark_count": 0,
          "impression_count": 0,
          "like_count": 0,
          "quote_count": 0,
          "reply_count": 0,
          "retweet_count": 0
        },
        "reply_settings": "everyone",
        "text": "648fo纪念～感谢大家🥰 https://t.co/zqRm9zd4RA"
      }
    ],
    "users": [
      {
        "created_at": "2024-01-31T03:44:57.000Z",
        "derived": {
          "locations": [
            {
              "country_code": "JP",
              "full_name": "Tokyo, Tōkyō, Japan",
              "geo": {
                "coordinates": [
                  139.69171,
                  35.6895
                ],
                "type": "Point"
              },
              "locality": "Tokyo",
              "region": "Tōkyō"
            }
          ]
        },
        "description": "温柔、善良、正直，只要你也追寻这些，就是我的好朋友❤️",
        "id": "1752538285459795968",
        "location": "東京",
        "name": "愿晚星照常升起🌈(keep4o)",
        "profile_image_url": "https://pbs.twimg.com/profile_images/2011352966788497408/fdBTaADg_normal.jpg",
        "protected": false,
        "public_metrics": {
          "followers_count": 648,
          "following_count": 611,
          "like_count": 102064,
          "listed_count": 10,
          "media_count": 580,
          "tweet_count": 7289
        },
        "username": "tadatsukiei",
        "verified": true
      }
    ]
  }
}