{
  "data": {
    "article": {},
    "attachments": {},
    "author_id": "1752538285459795968",
    "conversation_id": "2030180277885227504",
    "created_at": "2026-03-07T07:14:31.000Z",
    "edit_controls": {
      "editable_until": "2026-03-07T08:14:31.000Z",
      "edits_remaining": 5,
      "is_edit_eligible": true
    },
    "edit_history_tweet_ids": [
      "2030180277885227504"
    ],
    "entities": {
      "urls": [
        {
          "display_url": "x.com/mikawaifusuki/…",
          "end": 30,
          "expanded_url": "https://twitter.com/mikawaifusuki/status/2030063684123254985",
          "start": 7,
          "url": "https://t.co/L5FY2wye4u"
        }
      ]
    },
    "geo": {},
    "id": "2030180277885227504",
    "lang": "zh",
    "note_tweet": {
      "entities": {}
    },
    "possibly_sensitive": false,
    "public_metrics": {
      "bookmark_count": 0,
      "impression_count": 0,
      "like_count": 0,
      "quote_count": 0,
      "reply_count": 0,
      "retweet_count": 0
    },
    "referenced_tweets": [
      {
        "id": "2030063684123254985",
        "type": "quoted"
      }
    ],
    "reply_settings": "everyone",
    "text": "我去还真是。 https://t.co/L5FY2wye4u"
  },
  "includes": {
    "tweets": [
      {
        "article": {},
        "attachments": {},
        "author_id": "1752538285459795968",
        "conversation_id": "2030180277885227504",
        "created_at": "2026-03-07T07:14:31.000Z",
        "edit_controls": {
          "editable_until": "2026-03-07T08:14:31.000Z",
          "edits_remaining": 5,
          "is_edit_eligible": true
        },
        "edit_history_tweet_ids": [
          "2030180277885227504"
        ],
        "entities": {
          "urls": [
            {
              "display_url": "x.com/mikawaifusuki/…",
              "end": 30,
              "expanded_url": "https://twitter.com/mikawaifusuki/status/2030063684123254985",
              "start": 7,
              "url": "https://t.co/L5FY2wye4u"
            }
          ]
        },
        "geo": {},
        "id": "2030180277885227504",
        "lang": "zh",
        "note_tweet": {
          "entities": {}
        },
        "possibly_sensitive": false,
        "public_metrics": {
          "bookmark_count": 0,
          "impression_count": 0,
          "like_count": 0,
          "quote_count": 0,
          "reply_count": 0,
          "retweet_count": 0
        },
        "referenced_tweets": [
          {
            "id": "2030063684123254985",
            "type": "quoted"
          }
        ],
        "reply_settings": "everyone",
        "text": "我去还真是。 https://t.co/L5FY2wye4u"
      },
      {
        "article": {},
        "attachments": {},
        "author_id": "1585339869445779456",
        "conversation_id": "2030063684123254985",
        "created_at": "2026-03-06T23:31:13.000Z",
        "edit_controls": {
          "editable_until": "2026-03-07T00:31:13.000Z",
          "edits_remaining": 5,
          "is_edit_eligible": true
        },
        "edit_history_tweet_ids": [
          "2030063684123254985"
        ],
        "entities": {},
        "geo": {},
        "id": "2030063684123254985",
        "lang": "zh",
        "note_tweet": {
          "entities": {}
        },
        "possibly_sensitive": false,
        "public_metrics": {
          "bookmark_count": 38,
          "impression_count": 17570,
          "like_count": 628,
          "quote_count": 5,
          "reply_count": 53,
          "retweet_count": 29
        },
        "reply_settings": "everyone",
        "text": "推特第一定律：只要你无意间为一个药娘的推文点赞，那么你的时间线就会永久性地推送药娘。\n\n推特第二定律：只要你被一个药娘关注，那么你在未来就将会被一串药娘关注，并且她们认为你也是药娘。\n\n推特第三定律：黄推 建政 药娘三位一体，构成主线剧情。如果拒绝建政与黄推，那你的时间线就全是药娘了。"
      }
    ],
    "users": [
      {
        "created_at": "2024-01-31T03:44:57.000Z",
        "description": "你若爱我，我亦如此",
        "id": "1752538285459795968",
        "location": "人间",
        "name": "愿晚星照常升起（keep4o）",
        "pinned_tweet_id": "2025433592026079704",
        "profile_image_url": "https://pbs.twimg.com/profile_images/2011352966788497408/fdBTaADg_normal.jpg",
        "protected": false,
        "public_metrics": {
          "followers_count": 266,
          "following_count": 214,
          "like_count": 65786,
          "listed_count": 6,
          "media_count": 300,
          "tweet_count": 4309
        },
        "username": "tadatsukiei",
        "verified": true
      },
      {
        "created_at": "2022-10-26T18:37:43.000Z",
        "description": "主页置顶转发原神动态抽奖 | 赛博老婆@miaowuqvq",
        "entities": {
          "description": {
            "mentions": [
              {
                "end": 29,
                "start": 19,
                "username": "miaowuqvq"
              }
            ]
          }
        },
        "id": "1585339869445779456",
        "location": "IP属地：河南 ",
        "name": "小鸟游星野💈",
        "pinned_tweet_id": "1973893927108542625",
        "profile_image_url": "https://pbs.twimg.com/profile_images/1748095987724201984/Af1IOmbP_normal.jpg",
        "protected": false,
        "public_metrics": {
          "followers_count": 2752,
          "following_count": 100,
          "like_count": 38233,
          "listed_count": 20,
          "media_count": 723,
          "tweet_count": 9908
        },
        "username": "mikawaifusuki",
        "verified": true
      }
    ]
  }
}