{
  "data": {
    "article": {},
    "attachments": {},
    "author_id": "1752538285459795968",
    "conversation_id": "2075201177499709461",
    "created_at": "2026-07-09T16:30:56.000Z",
    "edit_controls": {
      "editable_until": "2026-07-09T17:30:56.000Z",
      "edits_remaining": 5,
      "is_edit_eligible": false
    },
    "edit_history_tweet_ids": [
      "2075256399320498222"
    ],
    "entities": {
      "mentions": [
        {
          "end": 13,
          "id": "1813561571941183488",
          "start": 0,
          "username": "careforme123"
        }
      ],
      "urls": [
        {
          "display_url": "x.com/tadatsukiei/st…",
          "end": 66,
          "expanded_url": "https://x.com/tadatsukiei/status/2054991530117800274?s=46",
          "start": 43,
          "url": "https://t.co/KO7KsXpIJr"
        }
      ]
    },
    "geo": {},
    "id": "2075256399320498222",
    "in_reply_to_user_id": "1813561571941183488",
    "lang": "zh",
    "note_tweet": {
      "entities": {}
    },
    "possibly_sensitive": false,
    "public_metrics": {
      "bookmark_count": 0,
      "impression_count": 0,
      "like_count": 0,
      "quote_count": 0,
      "reply_count": 0,
      "retweet_count": 0
    },
    "referenced_tweets": [
      {
        "id": "2054991530117800274",
        "type": "quoted"
      },
      {
        "id": "2075201177499709461",
        "type": "replied_to"
      }
    ],
    "reply_settings": "everyone",
    "text": "@careforme123 我一般不怎么用“键政”，毕竟在中文里这个词基本自带贬义。\nhttps://t.co/KO7KsXpIJr"
  },
  "includes": {
    "media": [
      {
        "height": 721,
        "media_key": "3_2075201161012068352",
        "public_metrics": {},
        "type": "photo",
        "url": "https://pbs.twimg.com/media/HMyYdgeaQAAl7vd.jpg",
        "width": 1115
      }
    ],
    "tweets": [
      {
        "article": {},
        "attachments": {},
        "author_id": "1752538285459795968",
        "conversation_id": "2075201177499709461",
        "created_at": "2026-07-09T16:30:56.000Z",
        "edit_controls": {
          "editable_until": "2026-07-09T17:30:56.000Z",
          "edits_remaining": 5,
          "is_edit_eligible": false
        },
        "edit_history_tweet_ids": [
          "2075256399320498222"
        ],
        "entities": {
          "mentions": [
            {
              "end": 13,
              "id": "1813561571941183488",
              "start": 0,
              "username": "careforme123"
            }
          ],
          "urls": [
            {
              "display_url": "x.com/tadatsukiei/st…",
              "end": 66,
              "expanded_url": "https://x.com/tadatsukiei/status/2054991530117800274?s=46",
              "start": 43,
              "url": "https://t.co/KO7KsXpIJr"
            }
          ]
        },
        "geo": {},
        "id": "2075256399320498222",
        "in_reply_to_user_id": "1813561571941183488",
        "lang": "zh",
        "note_tweet": {
          "entities": {}
        },
        "possibly_sensitive": false,
        "public_metrics": {
          "bookmark_count": 0,
          "impression_count": 0,
          "like_count": 0,
          "quote_count": 0,
          "reply_count": 0,
          "retweet_count": 0
        },
        "referenced_tweets": [
          {
            "id": "2054991530117800274",
            "type": "quoted"
          },
          {
            "id": "2075201177499709461",
            "type": "replied_to"
          }
        ],
        "reply_settings": "everyone",
        "text": "@careforme123 我一般不怎么用“键政”，毕竟在中文里这个词基本自带贬义。\nhttps://t.co/KO7KsXpIJr"
      },
      {
        "article": {},
        "attachments": {},
        "author_id": "1752538285459795968",
        "conversation_id": "2054938806806073760",
        "created_at": "2026-05-14T18:25:35.000Z",
        "edit_controls": {
          "editable_until": "2026-05-14T19:25:35.000Z",
          "edits_remaining": 5,
          "is_edit_eligible": false
        },
        "edit_history_tweet_ids": [
          "2054991530117800274"
        ],
        "entities": {
          "mentions": [
            {
              "end": 16,
              "id": "1586332050528915457",
              "start": 0,
              "username": "lilaoshizuikeai"
            }
          ]
        },
        "geo": {},
        "id": "2054991530117800274",
        "in_reply_to_user_id": "1586332050528915457",
        "lang": "zh",
        "note_tweet": {
          "entities": {},
          "text": "“键政”是中共污染汉语的最大实证，将“讨论政治”这一理所当然的公民权利污名化。键政键政——键盘上聊政治，给人一种脱离实际、纸上谈兵的印象，好像这是什么没用处、不该聊的事。\n当代中文互联网上的人往往听到政治讨论就退避三舍明哲保身“血别溅到我身上”，还常以看乐子的心态调侃或嘲讽。\n如今在任何中文政治讨论中，都能见到“键政”这个词，意思分中性和贬义。异见人士用键政指代“讨论（尤指中国）政治”，而在粉红基本盘口中就完全成了嘲讽。\n「讨论政治＝可耻」这个扭曲的观念已经被浓缩为“键政”一词刻入了我们当代华人的文化中，成为“莫谈国事”的更新版本。\n这难道不恐怖吗？"
        },
        "possibly_sensitive": false,
        "public_metrics": {
          "bookmark_count": 1,
          "impression_count": 504,
          "like_count": 23,
          "quote_count": 1,
          "reply_count": 1,
          "retweet_count": 3
        },
        "referenced_tweets": [
          {
            "id": "2054938806806073760",
            "type": "replied_to"
          }
        ],
        "reply_settings": "everyone",
        "text": "@lilaoshizuikeai “键政”是中共污染汉语的最大实证，将“讨论政治”这一理所当然的公民权利污名化。键政键政——键盘上聊政治，给人一种脱离实际、纸上谈兵的印象，好像这是什么没用处、不该聊的事。\n当代中文互联网上的人往往听到政治讨论就退避三舍明哲保身“血别溅到我身上”，还常以看乐子的心态调侃或嘲讽。"
      },
      {
        "article": {},
        "attachments": {
          "media_keys": [
            "3_2075201161012068352"
          ]
        },
        "author_id": "1813561571941183488",
        "conversation_id": "2075201177499709461",
        "created_at": "2026-07-09T12:51:30.000Z",
        "edit_controls": {
          "editable_until": "2026-07-09T13:51:30.000Z",
          "edits_remaining": 5,
          "is_edit_eligible": true
        },
        "edit_history_tweet_ids": [
          "2075201177499709461"
        ],
        "entities": {
          "urls": [
            {
              "display_url": "pic.x.com/ol9SugdNoP",
              "end": 167,
              "expanded_url": "https://x.com/careforme123/status/2075201177499709461/photo/1",
              "media_key": "3_2075201161012068352",
              "start": 144,
              "url": "https://t.co/ol9SugdNoP"
            }
          ]
        },
        "geo": {},
        "id": "2075201177499709461",
        "lang": "zh",
        "note_tweet": {
          "entities": {},
          "text": "在中国，键政是一种罪，你会被网友骂智商不如边牧\n\n然而，讨论政治，不是公民合法的权利吗？\n\n宪法第35条：中华人民共和国公民享有言论自由\n\n宪法第41条：公民对于任何国家机关和工作人员，有提出批评和建议的权利\n\n你们愿意放弃自己的权利，请别逼着别人放弃。你们骨子贱，请别逼着别人一起下跪"
        },
        "possibly_sensitive": false,
        "public_metrics": {
          "bookmark_count": 2,
          "impression_count": 574,
          "like_count": 35,
          "quote_count": 0,
          "reply_count": 2,
          "retweet_count": 4
        },
        "reply_settings": "everyone",
        "text": "在中国，键政是一种罪，你会被网友骂智商不如边牧\n\n然而，讨论政治，不是公民合法的权利吗？\n\n宪法第35条：中华人民共和国公民享有言论自由\n\n宪法第41条：公民对于任何国家机关和工作人员，有提出批评和建议的权利\n\n你们愿意放弃自己的权利，请别逼着别人放弃。你们骨子贱，请别逼着别人一起下跪 https://t.co/ol9SugdNoP"
      }
    ],
    "users": [
      {
        "created_at": "2024-01-31T03:44:57.000Z",
        "derived": {
          "locations": [
            {
              "country_code": "JP",
              "full_name": "Tokyo, Tōkyō, Japan",
              "geo": {
                "coordinates": [
                  139.69171,
                  35.6895
                ],
                "type": "Point"
              },
              "locality": "Tokyo",
              "region": "Tōkyō"
            }
          ]
        },
        "description": "温柔、善良、正直，只要你也追寻这些，就是我的好朋友❤️",
        "id": "1752538285459795968",
        "location": "東京",
        "name": "愿晚星照常升起🌈(keep4o)",
        "profile_image_url": "https://pbs.twimg.com/profile_images/2011352966788497408/fdBTaADg_normal.jpg",
        "protected": false,
        "public_metrics": {
          "followers_count": 730,
          "following_count": 668,
          "like_count": 110649,
          "listed_count": 5,
          "media_count": 656,
          "tweet_count": 7985
        },
        "url": "",
        "username": "tadatsukiei",
        "verified": true
      },
      {
        "created_at": "2024-07-17T13:09:16.000Z",
        "description": "女，现居日本",
        "id": "1813561571941183488",
        "name": "maybe🍥",
        "profile_image_url": "https://pbs.twimg.com/profile_images/2047660982370287616/9dQU-KLC_normal.jpg",
        "protected": false,
        "public_metrics": {
          "followers_count": 2550,
          "following_count": 793,
          "like_count": 7819,
          "listed_count": 9,
          "media_count": 804,
          "tweet_count": 3112
        },
        "url": "",
        "username": "careforme123",
        "verified": true
      }
    ]
  }
}