{
  "data": {
    "article": {},
    "attachments": {},
    "author_id": "1752538285459795968",
    "conversation_id": "2065360721681289478",
    "created_at": "2026-06-12T09:09:03.000Z",
    "edit_controls": {
      "editable_until": "2026-06-12T10:09:03.000Z",
      "edits_remaining": 5,
      "is_edit_eligible": false
    },
    "edit_history_tweet_ids": [
      "2065360721681289478"
    ],
    "entities": {
      "mentions": [
        {
          "end": 11,
          "id": "1239457591417171973",
          "start": 3,
          "username": "GFWfrog"
        }
      ]
    },
    "geo": {},
    "id": "2065360721681289478",
    "lang": "zh",
    "note_tweet": {
      "entities": {}
    },
    "possibly_sensitive": false,
    "public_metrics": {
      "bookmark_count": 0,
      "impression_count": 0,
      "like_count": 0,
      "quote_count": 0,
      "reply_count": 0,
      "retweet_count": 13
    },
    "referenced_tweets": [
      {
        "id": "2065337753584202092",
        "type": "retweeted"
      }
    ],
    "reply_settings": "everyone",
    "text": "RT @GFWfrog: 从6月10日晚上起，这位在重庆“山姆打包哥”虐狗示威现场拍照记录的女生已经持续失联了快48小时了，请大家给予关注！！"
  },
  "includes": {
    "tweets": [
      {
        "article": {},
        "attachments": {},
        "author_id": "1752538285459795968",
        "conversation_id": "2065360721681289478",
        "created_at": "2026-06-12T09:09:03.000Z",
        "edit_controls": {
          "editable_until": "2026-06-12T10:09:03.000Z",
          "edits_remaining": 5,
          "is_edit_eligible": false
        },
        "edit_history_tweet_ids": [
          "2065360721681289478"
        ],
        "entities": {
          "mentions": [
            {
              "end": 11,
              "id": "1239457591417171973",
              "start": 3,
              "username": "GFWfrog"
            }
          ]
        },
        "geo": {},
        "id": "2065360721681289478",
        "lang": "zh",
        "note_tweet": {
          "entities": {}
        },
        "possibly_sensitive": false,
        "public_metrics": {
          "bookmark_count": 0,
          "impression_count": 0,
          "like_count": 0,
          "quote_count": 0,
          "reply_count": 0,
          "retweet_count": 13
        },
        "referenced_tweets": [
          {
            "id": "2065337753584202092",
            "type": "retweeted"
          }
        ],
        "reply_settings": "everyone",
        "text": "RT @GFWfrog: 从6月10日晚上起，这位在重庆“山姆打包哥”虐狗示威现场拍照记录的女生已经持续失联了快48小时了，请大家给予关注！！"
      },
      {
        "article": {},
        "attachments": {},
        "author_id": "1239457591417171973",
        "conversation_id": "2065337753584202092",
        "created_at": "2026-06-12T07:37:47.000Z",
        "edit_controls": {
          "editable_until": "2026-06-12T08:37:47.000Z",
          "edits_remaining": 5,
          "is_edit_eligible": true
        },
        "edit_history_tweet_ids": [
          "2065337753584202092"
        ],
        "entities": {
          "urls": [
            {
              "display_url": "x.com/Oyama_Mihari01…",
              "end": 82,
              "expanded_url": "https://twitter.com/Oyama_Mihari01/status/2064369704698015951",
              "start": 59,
              "url": "https://t.co/fzFvprmBVY"
            }
          ]
        },
        "geo": {},
        "id": "2065337753584202092",
        "lang": "zh",
        "note_tweet": {
          "entities": {}
        },
        "possibly_sensitive": false,
        "public_metrics": {
          "bookmark_count": 4,
          "impression_count": 6847,
          "like_count": 103,
          "quote_count": 0,
          "reply_count": 8,
          "retweet_count": 13
        },
        "referenced_tweets": [
          {
            "id": "2064369704698015951",
            "type": "quoted"
          }
        ],
        "reply_settings": "everyone",
        "text": "从6月10日晚上起，这位在重庆“山姆打包哥”虐狗示威现场拍照记录的女生已经持续失联了快48小时了，请大家给予关注！！ https://t.co/fzFvprmBVY"
      }
    ],
    "users": [
      {
        "created_at": "2024-01-31T03:44:57.000Z",
        "derived": {
          "locations": [
            {
              "country_code": "JP",
              "full_name": "Tokyo, Tōkyō, Japan",
              "geo": {
                "coordinates": [
                  139.69171,
                  35.6895
                ],
                "type": "Point"
              },
              "locality": "Tokyo",
              "region": "Tōkyō"
            }
          ]
        },
        "description": "温柔、善良、正直，只要你也追寻这些，就是我的好朋友❤️",
        "id": "1752538285459795968",
        "location": "東京",
        "name": "愿晚星照常升起🌈(keep4o)",
        "profile_image_url": "https://pbs.twimg.com/profile_images/2011352966788497408/fdBTaADg_normal.jpg",
        "protected": false,
        "public_metrics": {
          "followers_count": 658,
          "following_count": 618,
          "like_count": 102322,
          "listed_count": 10,
          "media_count": 584,
          "tweet_count": 7326
        },
        "username": "tadatsukiei",
        "verified": true
      },
      {
        "created_at": "2020-03-16T07:44:59.000Z",
        "description": "投稿方式：私信 或 https://t.co/aVPvX0T16B 网页投稿 150岁爷习近平粉丝群：https://t.co/tzbqdA1XzO\n电报频道：https://t.co/Evu48wn45r \n#习近平150岁倒计时 #大自爆运动 #大冲塔运动 #大躺平运动 #不正确记忆\n邮箱：gfwfrog@gmail.com 🐸",
        "entities": {
          "description": {
            "hashtags": [
              {
                "end": 116,
                "start": 105,
                "tag": "习近平150岁倒计时"
              },
              {
                "end": 123,
                "start": 117,
                "tag": "大自爆运动"
              },
              {
                "end": 130,
                "start": 124,
                "tag": "大冲塔运动"
              },
              {
                "end": 137,
                "start": 131,
                "tag": "大躺平运动"
              },
              {
                "end": 144,
                "start": 138,
                "tag": "不正确记忆"
              }
            ],
            "urls": [
              {
                "display_url": "gfwbao.com",
                "end": 33,
                "expanded_url": "http://gfwbao.com",
                "start": 10,
                "url": "https://t.co/aVPvX0T16B"
              },
              {
                "display_url": "t.me/SpeedUpCN",
                "end": 74,
                "expanded_url": "http://t.me/SpeedUpCN",
                "start": 51,
                "url": "https://t.co/tzbqdA1XzO"
              },
              {
                "display_url": "t.me/XueXi_China",
                "end": 103,
                "expanded_url": "http://t.me/XueXi_China",
                "start": 80,
                "url": "https://t.co/Evu48wn45r"
              }
            ]
          },
          "url": {
            "urls": [
              {
                "display_url": "GFWbao.com",
                "end": 23,
                "expanded_url": "http://GFWbao.com",
                "start": 0,
                "url": "https://t.co/B3cyU85Q3u"
              }
            ]
          }
        },
        "id": "1239457591417171973",
        "location": "墙国",
        "name": "墙国蛙哈哈🐸",
        "pinned_tweet_id": "2058872944034558054",
        "profile_image_url": "https://pbs.twimg.com/profile_images/2050371764165767168/HypsUXGy_normal.jpg",
        "protected": false,
        "public_metrics": {
          "followers_count": 264815,
          "following_count": 2537,
          "like_count": 128283,
          "listed_count": 919,
          "media_count": 7502,
          "tweet_count": 14212
        },
        "url": "https://t.co/B3cyU85Q3u",
        "username": "GFWfrog",
        "verified": true
      }
    ]
  }
}